lazy/__init__.py
lazy_graph-0.3.17.dist-info/METADATA
lazy_graph-0.3.17.dist-info/WHEEL
lazy_graph-0.3.17.dist-info/top_level.txt
lazy_graph-0.3.17.dist-info/RECORD
