Metadata-Version: 2.1
Name: lazy_graph
Version: 0.3.17
Summary: lazy graph framework
Author-email: Hao Zhang <zh970205@mail.ustc.edu.cn>
License: GPLv3
Project-URL: Homepage, https://github.com/USTC-TNS/TNSP/tree/main/lazy_graph
Project-URL: Repository, https://github.com/USTC-TNS/TNSP.git
Project-URL: Issues, https://github.com/USTC-TNS/TNSP/issues
Project-URL: Changelog, https://github.com/USTC-TNS/TNSP/blob/main/CHANGELOG.org
Keywords: framework,lazy evaluation,computational graph
Classifier: Development Status :: 4 - Beta
Classifier: Programming Language :: Python :: 3
Classifier: License :: OSI Approved :: GNU General Public License v3 or later (GPLv3+)
Classifier: Topic :: Scientific/Engineering :: Mathematics
Classifier: Topic :: Scientific/Engineering :: Physics
Classifier: Topic :: Software Development :: Libraries :: Python Modules
Requires-Python: >=3.7
